{"dire_series_wins": 0, "dire_team_name": "", "game_number": 0, "league": {"league_id": 4122, "name": "FACEIT League", "tournament_url": "https://play.faceit.com/"}, "league_game_id": 0, "league_tier": "Amateur", "match_id": 2532709414, "radiant_series_wins": 0, "radiant_team_name": "", "scoreboard": {"day_cycle": "day", "dire": {"bans": ["vengefulspirit", "beastmaster", "death_prophet", "tidehunter", "ember_spirit"], "barracks_state": "111111", "picks": ["ancient_apparition", "doom_bringer", "zuus", "juggernaut", "tinker"], "players": [{"assists": 3, "death": 8, "position_y": 2256, "name": "Loafer-", "gold_per_min": 329, "level": 9, "last_hits": 82, "kills": 0, "ultimate_cooldown": 42, "hero": "juggernaut", "denies": 7, "ultimate_state": 1, "xp_per_min": 268, "position_x": 1700, "player_slot": 1, "respawn_timer": 0, "account_id": 170077363, "net_worth": 5507, "items": ["blade_of_alacrity", "poor_mans_shield", "helm_of_the_dominator", "phase_boots", "tpscroll", "quelling_blade"], "hero_id": 8, "gold": 267}, {"assists": 0, "death": 2, "position_y": 5598, "name": "AndriY", "gold_per_min": 483, "level": 13, "last_hits": 100, "kills": 6, "ultimate_cooldown": 0, "hero": "tinker", "denies": 5, "ultimate_state": 3, "xp_per_min": 511, "position_x": -4811, "player_slot": 2, "respawn_timer": 0, "account_id": 255853712, "net_worth": 9928, "items": ["dagon", "blink", "bottle", "travel_boots", "soul_ring", "faerie_fire"], "hero_id": 34, "gold": 1048}, {"assists": 4, "death": 7, "position_y": 6104, "name": "Koneko chan", "gold_per_min": 161, "level": 8, "last_hits": 7, "kills": 1, "ultimate_cooldown": 0, "hero": "zuus", "denies": 4, "ultimate_state": 3, "xp_per_min": 206, "position_x": 6860, "player_slot": 3, "respawn_timer": 0, "account_id": 166392891, "net_worth": 2071, "items": ["null_talisman", "boots", "dust", "None", "bottle", "tpscroll"], "hero_id": 22, "gold": 311}, {"assists": 3, "death": 5, "position_y": -83, "name": "SeGa", "gold_per_min": 190, "level": 8, "last_hits": 5, "kills": 2, "ultimate_cooldown": 0, "hero": "ancient_apparition", "denies": 4, "ultimate_state": 3, "xp_per_min": 174, "position_x": 1688, "player_slot": 4, "respawn_timer": 30, "account_id": 224049153, "net_worth": 2372, "items": ["tpscroll", "tranquil_boots", "ward_observer", "None", "None", "None"], "hero_id": 68, "gold": 1357}, {"assists": 3, "death": 4, "position_y": 628, "name": "diza_omg", "gold_per_min": 350, "level": 11, "last_hits": 69, "kills": 1, "ultimate_cooldown": 17, "hero": "doom_bringer", "denies": 0, "ultimate_state": 1, "xp_per_min": 380, "position_x": 1438, "player_slot": 5, "respawn_timer": 0, "account_id": 225220375, "net_worth": 6061, "items": ["boots", "stout_shield", "ancient_janggo", "None", "ring_of_basilius", "invis_sword"], "hero_id": 69, "gold": 476}], "score": 10, "tower_state": "11111111110"}, "duration": 1181, "radiant": {"bans": ["sven", "medusa", "bloodseeker", "undying", "morphling"], "barracks_state": "111111", "picks": ["slark", "disruptor", "bristleback", "elder_titan", "phantom_assassin"], "players": [{"assists": 12, "death": 3, "position_y": 91, "name": "Dark Knight", "gold_per_min": 262, "level": 11, "last_hits": 18, "kills": 3, "ultimate_cooldown": 0, "hero": "elder_titan", "denies": 3, "ultimate_state": 3, "xp_per_min": 358, "position_x": 812, "player_slot": 1, "respawn_timer": 0, "account_id": 108667679, "net_worth": 4617, "items": ["magic_wand", "arcane_boots", "mekansm", "ward_dispenser", "None", "None"], "hero_id": 103, "gold": 247}, {"assists": 3, "death": 4, "position_y": -1458, "name": "\u221a", "gold_per_min": 472, "level": 14, "last_hits": 97, "kills": 9, "ultimate_cooldown": 0, "hero": "slark", "denies": 1, "ultimate_state": 3, "xp_per_min": 536, "position_x": 2537, "player_slot": 2, "respawn_timer": 0, "account_id": 254767135, "net_worth": 8464, "items": ["invis_sword", "ring_of_aquila", "quelling_blade", "poor_mans_shield", "None", "power_treads"], "hero_id": 93, "gold": 79}, {"assists": 6, "death": 1, "position_y": -5163, "name": "IFRDYU", "gold_per_min": 331, "level": 11, "last_hits": 36, "kills": 9, "ultimate_cooldown": 0, "hero": "bristleback", "denies": 1, "ultimate_state": 3, "xp_per_min": 370, "position_x": 5514, "player_slot": 3, "respawn_timer": 0, "account_id": 187006432, "net_worth": 6450, "items": ["tpscroll", "magic_wand", "ring_of_basilius", "vanguard", "power_treads", "chainmail"], "hero_id": 99, "gold": 185}, {"assists": 2, "death": 1, "position_y": -4951, "name": "Yamaluxe\u2122", "gold_per_min": 216, "level": 9, "last_hits": 19, "kills": 3, "ultimate_cooldown": 0, "hero": "disruptor", "denies": 0, "ultimate_state": 3, "xp_per_min": 263, "position_x": -6335, "player_slot": 4, "respawn_timer": 0, "account_id": 63678824, "net_worth": 4238, "items": ["None", "mekansm", "arcane_boots", "None", "None", "None"], "hero_id": 87, "gold": 663}, {"assists": 8, "death": 1, "position_y": -5812, "name": "13", "gold_per_min": 350, "level": 11, "last_hits": 95, "kills": 2, "ultimate_cooldown": 0, "hero": "phantom_assassin", "denies": 7, "ultimate_state": 3, "xp_per_min": 394, "position_x": 4534, "player_slot": 5, "respawn_timer": 0, "account_id": 108463175, "net_worth": 6386, "items": ["helm_of_iron_will", "power_treads", "quelling_blade", "helm_of_the_dominator", "ring_of_aquila", "tpscroll"], "hero_id": 44, "gold": 51}], "score": 26, "tower_state": "11110111110"}, "roshan_respawn_timer": 0}, "series_type": "None", "spectators": 1, "stage_name": "", "stream_delay_s": 300}